[
    {
        "_id": "1026",
        "image": "https://i.ibb.co/qM3qpyZ/angkor-wat-11zon.jpg",
        "tourists_spot_name": "Angkor Wat",
        "country_Name": "Cambodia",
        "location": "Siem Reap, Cambodia",
        "short_description": "A massive temple complex and the largest religious monument in the world.",
        "average_cost": 450,
        "seasonality": "Spring",
        "travel_time": "5 days",
        "totalVisitorsPerYear": 30000,
        "user_email": "example@user.com",
        "user_name": "Sophia Lee"
    },
    {
        "_id": "1008",
        "image": "https://i.ibb.co/bK352bx/ayutthaya-11zon.jpg",
        "tourists_spot_name": "Ayutthaya",
        "country_Name": "Thailand",
        "location": "Ayutthaya, Thailand",
        "short_description": "An ancient capital of Thailand, known for its archaeological ruins.",
        "average_cost": 400,
        "seasonality": "Spring",
        "travel_time": "3 days",
        "totalVisitorsPerYear": 13000,
        "user_email": "example@user.com",
        "user_name": "Jane Smith"
    },
    {
        "_id": "1011",
        "image": "https://i.ibb.co/vC9DDLd/bali-11zon.jpg",
        "tourists_spot_name": "Bali",
        "country_Name": "Indonesia",
        "location": "Bali, Indonesia",
        "short_description": "An island known for its volcanic mountains, rice paddies, and coral reefs.",
        "average_cost": 600,
        "seasonality": "Spring",
        "travel_time": "7 days",
        "totalVisitorsPerYear": 20000,
        "user_email": "example@user.com",
        "user_name": "Emily Davis"
    },
    {
        "_id": "1004",
        "image": "https://i.ibb.co/Tqqqqx5/bandarban-11zon.jpg",
        "tourists_spot_name": "Bandarban",
        "country_Name": "Bangladesh",
        "location": "Chittagong Division, Bangladesh",
        "short_description": "A hilly district with waterfalls, tribal villages, and lush green hills.",
        "average_cost": 350,
        "seasonality": "Winter",
        "travel_time": "4 days",
        "totalVisitorsPerYear": 10000,
        "user_email": "example@user.com",
        "user_name": "Michael Brown"
    },
    {
        "_id": "1006",
        "image": "https://i.ibb.co/60ntB0Q/bangkok-11zon.jpg",
        "tourists_spot_name": "Bangkok",
        "country_Name": "Thailand",
        "location": "Bangkok, Thailand",
        "short_description": "Thailand's capital, known for ornate shrines and vibrant street life.",
        "average_cost": 600,
        "seasonality": "Summer",
        "travel_time": "4 days",
        "totalVisitorsPerYear": 20000,
        "user_email": "example@user.com",
        "user_name": "Sophia Lee"
    },
    {
        "_id": "1030",
        "image": "https://i.ibb.co/tYszgZ8/bokor-national-park-11zon.jpg",
        "tourists_spot_name": "Bokor National Park",
        "country_Name": "Cambodia",
        "location": "Kampot Province, Cambodia",
        "short_description": "Known for its cooler climate, scenic views, and historical French colonial hill station.",
        "average_cost": 350,
        "seasonality": "Spring",
        "travel_time": "3 days",
        "totalVisitorsPerYear": 11000,
        "user_email": "example@user.com",
        "user_name": "Emily Davis"
    },
    {
        "_id": "1012",
        "image": "https://i.ibb.co/C73PdCx/borobudur-temple-11zon.jpg",
        "tourists_spot_name": "Borobudur Temple",
        "country_Name": "Indonesia",
        "location": "Magelang, Indonesia",
        "short_description": "A 9th-century Mahayana Buddhist temple and a UNESCO World Heritage site.",
        "average_cost": 500,
        "seasonality": "Summer",
        "travel_time": "3 days",
        "totalVisitorsPerYear": 17000,
        "user_email": "example@user.com",
        "user_name": "Sophia Lee"
    },   
    {
        "_id": "1019",
        "image": "https://i.ibb.co/BCyqSfS/cameron-highlands-11zon.jpg",
        "tourists_spot_name": "Cameron Highlands",
        "country_Name": "Malaysia",
        "location": "Pahang, Malaysia",
        "short_description": "Known for its tea plantations, cool climate, and strawberry farms.",
        "average_cost": 350,
        "seasonality": "Spring",
        "travel_time": "4 days",
        "totalVisitorsPerYear": 13000,
        "user_email": "example@user.com",
        "user_name": "John Doe"
    }, 
    {
        "_id": "1007",
        "image": "https://i.ibb.co/Y8xgTR3/chiang-mai-11zon.jpg",
        "tourists_spot_name": "Chiang Mai",
        "country_Name": "Thailand",
        "location": "Chiang Mai, Thailand",
        "short_description": "A city in mountainous northern Thailand known for its temples and night bazaars.",
        "average_cost": 500,
        "seasonality": "Winter",
        "travel_time": "5 days",
        "totalVisitorsPerYear": 14000,
        "user_email": "example@user.com",
        "user_name": "John Doe"
    },
    {
        "_id": "1002",
        "image": "https://i.ibb.co/s1nLfmv/coxs-bazar-11zon.jpg",
        "tourists_spot_name": "Cox's Bazar",
        "country_Name": "Bangladesh",
        "location": "Cox's Bazar District, Bangladesh",
        "short_description": "The world's longest natural sea beach, famous for its beautiful sunset views.",
        "average_cost": 400,
        "seasonality": "Summer",
        "travel_time": "3 days",
        "totalVisitorsPerYear": 12000,
        "user_email": "example@user.com",
        "user_name": "Jane Smith"
    },
    {
        "_id": "1021",
        "image": "https://i.ibb.co/k8ShZFJ/ha-long-bay-11zon.webp",
        "tourists_spot_name": "Ha Long Bay",
        "country_Name": "Vietnam",
        "location": "Quang Ninh Province, Vietnam",
        "short_description": "Famous for its emerald waters and thousands of limestone islands.",
        "average_cost": 550,
        "seasonality": "Winter",
        "travel_time": "6 days",
        "totalVisitorsPerYear": 22000,
        "user_email": "example@user.com",
        "user_name": "Alice Johnson"
    },
    {
        "_id": "1022",
        "image": "https://i.ibb.co/Z190qyk/ho-ghi-minh-city-11zon.jpg",
        "tourists_spot_name": "Ho Chi Minh City",
        "country_Name": "Vietnam",
        "location": "Ho Chi Minh City, Vietnam",
        "short_description": "A bustling city known for its French colonial landmarks and vibrant street food scene.",
        "average_cost": 400,
        "seasonality": "Summer",
        "travel_time": "4 days",
        "totalVisitorsPerYear": 19000,
        "user_email": "example@user.com",
        "user_name": "Michael Brown"
    },
    {
        "_id": "1023",
        "image": "https://i.ibb.co/tqLHrSS/hoi-an-ancient-town-11zon.jpg",
        "tourists_spot_name": "Hoi An Ancient Town",
        "country_Name": "Vietnam",
        "location": "Quang Nam Province, Vietnam",
        "short_description": "A well-preserved ancient town known for its mix of various architectural styles.",
        "average_cost": 450,
        "seasonality": "Spring",
        "travel_time": "5 days",
        "totalVisitorsPerYear": 16000,
        "user_email": "example@user.com",
        "user_name": "Emily Davis"
    },
    {
        "_id": "1029",
        "image": "https://i.ibb.co/7RZC4s3/kep-11zon.jpg",
        "tourists_spot_name": "Kep",
        "country_Name": "Cambodia",
        "location": "Kep, Cambodia",
        "short_description": "A coastal city known for its seafood and quiet beaches.",
        "average_cost": 300,
        "seasonality": "Autumn",
        "travel_time": "2 days",
        "totalVisitorsPerYear": 9000,
        "user_email": "example@user.com",
        "user_name": "Jane Smith"
    },
    {
        "_id": "1013",
        "image": "https://i.ibb.co/StgYRtS/komodo-national-park-11zon.jpg",
        "tourists_spot_name": "Komodo National Park",
        "country_Name": "Indonesia",
        "location": "East Nusa Tenggara, Indonesia",
        "short_description": "Home to the Komodo dragon and known for its coral reefs and hiking trails.",
        "average_cost": 650,
        "seasonality": "Winter",
        "travel_time": "5 days",
        "totalVisitorsPerYear": 14000,
        "user_email": "example@user.com",
        "user_name": "John Doe"
    },
    {
        "_id": "1016",
        "image": "https://i.ibb.co/MsX9pxn/kuala-lumpur-11zon.jpg",
        "tourists_spot_name": "Kuala Lumpur",
        "country_Name": "Malaysia",
        "location": "Kuala Lumpur, Malaysia",
        "short_description": "The capital city known for its modern skyline and the iconic Petronas Towers.",
        "average_cost": 550,
        "seasonality": "Winter",
        "travel_time": "5 days",
        "totalVisitorsPerYear": 18000,
        "user_email": "example@user.com",
        "user_name": "Michael Brown"
    },
    {
        "_id": "1017",
        "image": "https://i.ibb.co/2vqp92S/langkawi-11zon.jpg",
        "tourists_spot_name": "Langkawi",
        "country_Name": "Malaysia",
        "location": "Langkawi, Malaysia",
        "short_description": "A beautiful archipelago known for its beaches, clear waters, and duty-free shopping.",
        "average_cost": 400,
        "seasonality": "Autumn",
        "travel_time": "3 days",
        "totalVisitorsPerYear": 15000,
        "user_email": "example@user.com",
        "user_name": "Emily Davis"
    },
    {
        "_id": "1025",
        "image": "https://i.ibb.co/mGRKNTL/mekong-delta-11zon.jpg",
        "tourists_spot_name": "Mekong Delta",
        "country_Name": "Vietnam",
        "location": "Southern Vietnam",
        "short_description": "Known for its rivers, floating markets, and lush green landscapes.",
        "average_cost": 500,
        "seasonality": "Autumn",
        "travel_time": "5 days",
        "totalVisitorsPerYear": 18000,
        "user_email": "example@user.com",
        "user_name": "Jane Smith"
    },
    {
        "_id": "1018",
        "image": "https://i.ibb.co/nsJdZsF/penang-11zon.jpg",
        "tourists_spot_name": "Penang",
        "country_Name": "Malaysia",
        "location": "George Town, Malaysia",
        "short_description": "Known for its historic George Town, delicious street food, and cultural heritage.",
        "average_cost": 450,
        "seasonality": "Summer",
        "travel_time": "4 days",
        "totalVisitorsPerYear": 17000,
        "user_email": "example@user.com",
        "user_name": "Sophia Lee"
    },
    {
        "_id": "1010",
        "image": "https://i.ibb.co/rvDkgQ9/phi-phi-islands-11zon.jpg",
        "tourists_spot_name": "Phi Phi Islands",
        "country_Name": "Thailand",
        "location": "Krabi Province, Thailand",
        "short_description": "An island group known for its crystal-clear waters and limestone cliffs.",
        "average_cost": 550,
        "seasonality": "Autumn",
        "travel_time": "5 days",
        "totalVisitorsPerYear": 16000,
        "user_email": "example@user.com",
        "user_name": "Michael Brown"
    },
    {
        "_id": "1028",
        "image": "https://i.ibb.co/qj3Cq1k/phnom-penh-11zon.jpg",
        "tourists_spot_name": "Phnom Penh",
        "country_Name": "Cambodia",
        "location": "Phnom Penh, Cambodia",
        "short_description": "The capital city known for its historical sites, including the Royal Palace.",
        "average_cost": 400,
        "seasonality": "Summer",
        "travel_time": "3 days",
        "totalVisitorsPerYear": 12000,
        "user_email": "example@user.com",
        "user_name": "Michael Brown"
    },
    {
        "_id": "1024",
        "image": "https://i.ibb.co/HqywVs5/phong-nha-caves-11zon.jpg",
        "tourists_spot_name": "Phong Nha Caves",
        "country_Name": "Vietnam",
        "location": "Quang Binh Province, Vietnam",
        "short_description": "A UNESCO World Heritage site known for its cave systems and karst mountains.",
        "average_cost": 600,
        "seasonality": "Winter",
        "travel_time": "4 days",
        "totalVisitorsPerYear": 14000,
        "user_email": "example@user.com",
        "user_name": "John Doe"
    },
    {
        "_id": "1009",
        "image": "https://i.ibb.co/j8rZMf4/phuket-11zon.jpg",
        "tourists_spot_name": "Phuket",
        "country_Name": "Thailand",
        "location": "Phuket, Thailand",
        "short_description": "Known for its stunning beaches, vibrant nightlife, and water activities.",
        "average_cost": 700,
        "seasonality": "Summer",
        "travel_time": "4 days",
        "totalVisitorsPerYear": 25000,
        "user_email": "example@user.com",
        "user_name": "Alice Johnson"
    },
    {
        "_id": "1014",
        "image": "https://i.ibb.co/rwszJ04/raja-ampat-islands-11zon.jpg",
        "tourists_spot_name": "Raja Ampat Islands",
        "country_Name": "Indonesia",
        "location": "West Papua, Indonesia",
        "short_description": "Known for its coral reefs, marine life, and pristine beaches.",
        "average_cost": 800,
        "seasonality": "Autumn",
        "travel_time": "6 days",
        "totalVisitorsPerYear": 11000,
        "user_email": "example@user.com",
        "user_name": "Jane Smith"
    },
    {
        "_id": "1003",
        "image": "https://i.ibb.co/6ZrM0PJ/rangamati-11zon.jpg",
        "tourists_spot_name": "Rangamati",
        "country_Name": "Bangladesh",
        "location": "Chittagong Hill Tracts, Bangladesh",
        "short_description": "Known for its hills, lakes, and the beautiful Kaptai Lake.",
        "average_cost": 300,
        "seasonality": "Autumn",
        "travel_time": "2 days",
        "totalVisitorsPerYear": 9000,
        "user_email": "example@user.com",
        "user_name": "Alice Johnson"
    },
    {
        "_id": "1005",
        "image": "https://i.ibb.co/cyKc5t6/saint-martin-island-11zon.jpg",
        "tourists_spot_name": "Saint Martin's Island",
        "country_Name": "Bangladesh",
        "location": "Cox's Bazar District, Bangladesh",
        "short_description": "The only coral island in Bangladesh, known for its clear blue waters.",
        "average_cost": 450,
        "seasonality": "Spring",
        "travel_time": "3 days",
        "totalVisitorsPerYear": 11000,
        "user_email": "example@user.com",
        "user_name": "Emily Davis"
    },
    {
        "_id": "1027",
        "image": "https://i.ibb.co/CvfVwQC/siem-reap-11zon.jpg",
        "tourists_spot_name": "Siem Reap",
        "country_Name": "Cambodia",
        "location": "Siem Reap, Cambodia",
        "short_description": "The gateway to the ruins of Angkor Wat and known for its vibrant culture.",
        "average_cost": 500,
        "seasonality": "Winter",
        "travel_time": "4 days",
        "totalVisitorsPerYear": 14000,
        "user_email": "example@user.com",
        "user_name": "Alice Johnson"
    },
    {
        "_id": "1001",
        "image": "https://i.ibb.co/1J9HSSZ/sundarban-11zon.jpg",
        "tourists_spot_name": "Sundarban",
        "country_Name": "Bangladesh",
        "location": "Khulna Division, Bangladesh",
        "short_description": "The world's largest mangrove forest and home to the Royal Bengal Tiger.",
        "average_cost": 500,
        "seasonality": "Winter",
        "travel_time": "5 days",
        "totalVisitorsPerYear": 15000,
        "user_email": "example@user.com",
        "user_name": "John Doe"
    },
    {
        "_id": "1020",
        "image": "https://i.ibb.co/KX0qy8C/taman-negara-national-park-11zon.jpg",
        "tourists_spot_name": "Taman Negara National Park",
        "country_Name": "Malaysia",
        "location": "Pahang, Malaysia",
        "short_description": "One of the world's oldest tropical rainforests, known for trekking and wildlife.",
        "average_cost": 500,
        "seasonality": "Winter",
        "travel_time": "5 days",
        "totalVisitorsPerYear": 14000,
        "user_email": "example@user.com",
        "user_name": "Jane Smith"
    },
    {
        "_id": "1015",
        "image": "https://i.ibb.co/qYPYnP5/yogyakarta-11zon.jpg",
        "tourists_spot_name": "Yogyakarta",
        "country_Name": "Indonesia",
        "location": "Java, Indonesia",
        "short_description": "A city on the island of Java known for its traditional arts and cultural heritage.",
        "average_cost": 450,
        "seasonality": "Spring",
        "travel_time": "4 days",
        "totalVisitorsPerYear": 13000,
        "user_email": "example@user.com",
        "user_name": "Alice Johnson"
    }
]